<gpx>
	<trk>
		<trkseg>
				<trkpt lat="42.011816" lon="21.372273">
					<ele>255.055908</ele>
					<time>2018-03-10T16:02:05+0100</time>
				</trkpt>
				<trkpt lat="42.011818" lon="21.372269">
					<ele>256.107178</ele>
					<time>2018-03-10T16:02:06+0100</time>
				</trkpt>
				<trkpt lat="42.011822" lon="21.372266">
					<ele>254.402344</ele>
					<time>2018-03-10T16:02:07+0100</time>
				</trkpt>
				<trkpt lat="42.011822" lon="21.372260">
					<ele>252.182617</ele>
					<time>2018-03-10T16:02:08+0100</time>
				</trkpt>
				<trkpt lat="42.011823" lon="21.372256">
					<ele>251.661987</ele>
					<time>2018-03-10T16:02:09+0100</time>
				</trkpt>
				<trkpt lat="42.011823" lon="21.372256">
					<ele>249.293823</ele>
					<time>2018-03-10T16:02:10+0100</time>
				</trkpt>
				<trkpt lat="42.011826" lon="21.372255">
					<ele>248.787964</ele>
					<time>2018-03-10T16:02:11+0100</time>
				</trkpt>
				<trkpt lat="42.011825" lon="21.372262">
					<ele>249.577393</ele>
					<time>2018-03-10T16:02:12+0100</time>
				</trkpt>
				<trkpt lat="42.011825" lon="21.372267">
					<ele>248.231873</ele>
					<time>2018-03-10T16:02:13+0100</time>
				</trkpt>
				<trkpt lat="42.011826" lon="21.372272">
					<ele>248.111450</ele>
					<time>2018-03-10T16:02:14+0100</time>
				</trkpt>
				<trkpt lat="42.011827" lon="21.372272">
					<ele>248.821411</ele>
					<time>2018-03-10T16:02:15+0100</time>
				</trkpt>
				<trkpt lat="42.011830" lon="21.372272">
					<ele>251.400269</ele>
					<time>2018-03-10T16:02:16+0100</time>
				</trkpt>
				<trkpt lat="42.011835" lon="21.372272">
					<ele>250.767090</ele>
					<time>2018-03-10T16:02:17+0100</time>
				</trkpt>
				<trkpt lat="42.011841" lon="21.372272">
					<ele>249.720337</ele>
					<time>2018-03-10T16:02:18+0100</time>
				</trkpt>
				<trkpt lat="42.011848" lon="21.372271">
					<ele>253.982178</ele>
					<time>2018-03-10T16:02:19+0100</time>
				</trkpt>
				<trkpt lat="42.011857" lon="21.372272">
					<ele>253.684204</ele>
					<time>2018-03-10T16:02:20+0100</time>
				</trkpt>
				<trkpt lat="42.011862" lon="21.372280">
					<ele>253.814941</ele>
					<time>2018-03-10T16:02:21+0100</time>
				</trkpt>
				<trkpt lat="42.011867" lon="21.372301">
					<ele>252.644043</ele>
					<time>2018-03-10T16:02:22+0100</time>
				</trkpt>
				<trkpt lat="42.011868" lon="21.372319">
					<ele>255.605774</ele>
					<time>2018-03-10T16:02:23+0100</time>
				</trkpt>
				<trkpt lat="42.011870" lon="21.372330">
					<ele>255.518311</ele>
					<time>2018-03-10T16:02:24+0100</time>
				</trkpt>
				<trkpt lat="42.011868" lon="21.372341">
					<ele>255.537476</ele>
					<time>2018-03-10T16:02:25+0100</time>
				</trkpt>
				<trkpt lat="42.011867" lon="21.372348">
					<ele>254.909729</ele>
					<time>2018-03-10T16:02:26+0100</time>
				</trkpt>
				<trkpt lat="42.011871" lon="21.372352">
					<ele>254.064941</ele>
					<time>2018-03-10T16:02:27+0100</time>
				</trkpt>
				<trkpt lat="42.011875" lon="21.372360">
					<ele>253.044800</ele>
					<time>2018-03-10T16:02:28+0100</time>
				</trkpt>
				<trkpt lat="42.011878" lon="21.372374">
					<ele>253.381470</ele>
					<time>2018-03-10T16:02:29+0100</time>
				</trkpt>
				<trkpt lat="42.011878" lon="21.372397">
					<ele>253.095886</ele>
					<time>2018-03-10T16:02:30+0100</time>
				</trkpt>
				<trkpt lat="42.011872" lon="21.372421">
					<ele>253.376953</ele>
					<time>2018-03-10T16:02:31+0100</time>
				</trkpt>
				<trkpt lat="42.011869" lon="21.372438">
					<ele>253.647766</ele>
					<time>2018-03-10T16:02:32+0100</time>
				</trkpt>
				<trkpt lat="42.011866" lon="21.372451">
					<ele>252.543274</ele>
					<time>2018-03-10T16:02:33+0100</time>
				</trkpt>
				<trkpt lat="42.011863" lon="21.372461">
					<ele>251.982788</ele>
					<time>2018-03-10T16:02:34+0100</time>
				</trkpt>
				<trkpt lat="42.011859" lon="21.372474">
					<ele>252.161255</ele>
					<time>2018-03-10T16:02:35+0100</time>
				</trkpt>
				<trkpt lat="42.011855" lon="21.372494">
					<ele>251.834839</ele>
					<time>2018-03-10T16:02:36+0100</time>
				</trkpt>
				<trkpt lat="42.011852" lon="21.372515">
					<ele>252.308167</ele>
					<time>2018-03-10T16:02:37+0100</time>
				</trkpt>
				<trkpt lat="42.011851" lon="21.372532">
					<ele>251.825806</ele>
					<time>2018-03-10T16:02:38+0100</time>
				</trkpt>
				<trkpt lat="42.011850" lon="21.372550">
					<ele>251.138245</ele>
					<time>2018-03-10T16:02:39+0100</time>
				</trkpt>
				<trkpt lat="42.011849" lon="21.372560">
					<ele>249.330688</ele>
					<time>2018-03-10T16:02:40+0100</time>
				</trkpt>
				<trkpt lat="42.011847" lon="21.372563">
					<ele>250.974121</ele>
					<time>2018-03-10T16:02:41+0100</time>
				</trkpt>
				<trkpt lat="42.011849" lon="21.372558">
					<ele>250.327576</ele>
					<time>2018-03-10T16:02:42+0100</time>
				</trkpt>
				<trkpt lat="42.011851" lon="21.372551">
					<ele>250.280151</ele>
					<time>2018-03-10T16:02:43+0100</time>
				</trkpt>
		</trkseg>
	</trk>
</gpx>